<?xml version="1.0" encoding="UTF-8"?>
<record_update table="sys_metadata_link">
    <sys_metadata_link action="INSERT_OR_UPDATE">
        <directory>unload</directory>
        <documentkey>com.snc.assessment_core</documentkey>
        <payload>&lt;?xml version="1.0" encoding="UTF-8"?&gt;
&lt;record_update table="v_plugin"&gt;
    &lt;v_plugin action="INSERT_OR_UPDATE"&gt;
        &lt;active&gt;active&lt;/active&gt;
        &lt;available_version&gt;1.0.0&lt;/available_version&gt;
        &lt;definition&gt;&lt;![CDATA[&lt;?xml version="1.0" encoding="utf-8" ?&gt;
&lt;plugin id="com.snc.assessment_core" name="Assessment" version="1.0.0" state="published" help="Assessments" type="application"
	provider_name="ServiceNow" licensable="true" namespace="sn_assessment_core" license_model="producer"&gt;

	&lt;extension point="com.glide.ajax.processors" name="AssessmentEngineAjax" class="com.snc.assessment_core.AssessmentEngineAjax" /&gt;
	&lt;extension point="com.glide.ui.jelly" name="com.snc.assessment_core_take" class="com.snc.assessment_core.TakeAssessment" /&gt;
	&lt;extension point="com.glide.ui.jelly" name="com.snc.asmt_attachment_list" class="com.snc.assessment_core.AssessmentAttachmentTag" /&gt;
	&lt;description&gt;
		Plug-in for Assessments, Surveys and Ratings
	&lt;/description&gt;
	
	 &lt;requires&gt;
		&lt;import plugin="com.glideapp.workflow"/&gt;
		&lt;import plugin="com.glideapp.survey"/&gt;
		&lt;import plugin="com.snc.bestpractice.task_survey"/&gt;
		&lt;import plugin="com.glide.survey_designer"/&gt;
     &lt;/requires&gt;
	&lt;extension point="com.glide.ajax.processors" name="ScorecardAjax" class="com.snc.assessment_core.ScorecardAjax" /&gt;
	&lt;extension point="com.glide.ajax.processors" name="ComparisonAjax" class="com.snc.assessment_core.ComparisonAjax" /&gt;
	&lt;extension point="com.glide.ajax.processors" name="DecisionMatrixAjax" class="com.snc.assessment_core.DecisionMatrixAjax" /&gt;
	&lt;extension point="com.glide.scriptable_object" name="AssessmentCreation" class="com.snc.assessment_core.AssessmentCreation" /&gt;
	&lt;extension point="com.glide.scriptable_object" name="ScopedAssessmentCreation" class="com.snc.assessment_core.ScopedAssessmentCreation"/&gt;
	&lt;extension point="com.glide.scriptable_object" name="SetAssessmentResults" class="com.snc.assessment_core.SetAssessmentResults" /&gt;
	&lt;extension point="com.glide.scriptable_object" name="Rating" class="com.snc.assessment_core.Rating" /&gt;
	&lt;extension point="com.glide.scriptable_object" name="AssessmentUpgradeHelper" class="com.snc.assessment_core.AssessmentUpgradeHelper" /&gt;
&lt;/plugin&gt;]]&gt;&lt;/definition&gt;
        &lt;description&gt;Plug-in for Assessments, Surveys and Ratings&lt;/description&gt;
        &lt;has_demo_data&gt;true&lt;/has_demo_data&gt;
        &lt;help&gt;http://docs.servicenow.com/?context=Assessments&lt;/help&gt;
        &lt;id&gt;com.snc.assessment_core&lt;/id&gt;
        &lt;licensable&gt;true&lt;/licensable&gt;
        &lt;name&gt;Assessment&lt;/name&gt;
        &lt;path&gt;plugin://com.snc.assessment_core/&lt;/path&gt;
        &lt;provider&gt;ServiceNow&lt;/provider&gt;
        &lt;requires&gt;com.glideapp.workflow,com.glideapp.survey,com.snc.bestpractice.task_survey,com.glide.survey_designer&lt;/requires&gt;
        &lt;scope&gt;global&lt;/scope&gt;
        &lt;state&gt;published&lt;/state&gt;
        &lt;supports_rollback&gt;false&lt;/supports_rollback&gt;
        &lt;sys_created_by&gt;admin&lt;/sys_created_by&gt;
        &lt;sys_created_on&gt;2017-12-05 06:05:22&lt;/sys_created_on&gt;
        &lt;sys_id&gt;com.snc.assessment_core&lt;/sys_id&gt;
        &lt;sys_mod_count&gt;0&lt;/sys_mod_count&gt;
        &lt;sys_updated_by&gt;admin&lt;/sys_updated_by&gt;
        &lt;sys_updated_on&gt;2017-12-05 06:05:22&lt;/sys_updated_on&gt;
        &lt;trackable&gt;true&lt;/trackable&gt;
        &lt;type&gt;application&lt;/type&gt;
        &lt;version&gt;1.0.0&lt;/version&gt;
    &lt;/v_plugin&gt;
&lt;/record_update&gt;
</payload>
        <sys_class_name>sys_metadata_link</sys_class_name>
        <sys_created_by>admin</sys_created_by>
        <sys_created_on>2017-12-05 06:30:47</sys_created_on>
        <sys_customer_update>true</sys_customer_update>
        <sys_id>33bf96564f320300fd1ce9628110c7c9</sys_id>
        <sys_mod_count>0</sys_mod_count>
        <sys_name>Assessment</sys_name>
        <sys_package display_value="Plugin Xplore" source="x_22847_plugin_xpl">64db9e524f320300fd1ce9628110c747</sys_package>
        <sys_policy/>
        <sys_replace_on_upgrade>false</sys_replace_on_upgrade>
        <sys_scope display_value="Plugin Xplore">64db9e524f320300fd1ce9628110c747</sys_scope>
        <sys_update_name>sys_metadata_link_33bf96564f320300fd1ce9628110c7c9</sys_update_name>
        <sys_updated_by>admin</sys_updated_by>
        <sys_updated_on>2017-12-05 06:30:47</sys_updated_on>
        <tablename>v_plugin</tablename>
    </sys_metadata_link>
</record_update>
